snapreq/__init__.py
snapreq/cli.py
snapreq/console/__init__.py
snapreq/console/logger.py
snapreq/console/utils.py
snapreq/utils/__init__.py
snapreq/utils/file_writter.py
snapreq/utils/handlers.py
snapreq/utils/methods.py
snapreq/utils/transformers.py
snapreq-1.1.0.dist-info/LICENSE
snapreq-1.1.0.dist-info/METADATA
snapreq-1.1.0.dist-info/WHEEL
snapreq-1.1.0.dist-info/entry_points.txt
snapreq-1.1.0.dist-info/top_level.txt
snapreq-1.1.0.dist-info/RECORD
