Metadata-Version: 2.1
Name: snapreq
Version: 1.1.0
Summary: A CLI-Based API Client for Simplified API Testing
Home-page: https://github.com/rnium/snapreq
Author: Md. Saiful Islam Roni
License: UNKNOWN
Platform: UNKNOWN
Classifier: Programming Language :: Python :: 3.10
Classifier: License :: OSI Approved :: MIT License
Classifier: Operating System :: OS Independent
Requires-Python: >=3.10
License-File: LICENSE
Requires-Dist: rich>=13.9
Requires-Dist: requests>=2.32
